{
	"ImportPath": "github.com/RaganH/eloweb",
	"GoVersion": "go1.6",
	"GodepVersion": "v69",
	"Packages": [
		"./..."
	],
	"Deps": [
		{
			"ImportPath": "github.com/davecgh/go-spew/spew",
			"Rev": "5215b55f46b2b919f50a1df0eaa5886afe4e3b3d"
		},
		{
			"ImportPath": "github.com/gin-gonic/gin",
			"Comment": "v1.0rc1-110-g4cc2de6",
			"Rev": "4cc2de6207f4128624cbdd16be30f64966c67c08"
		},
		{
			"ImportPath": "github.com/gin-gonic/gin/binding",
			"Comment": "v1.0rc1-110-g4cc2de6",
			"Rev": "4cc2de6207f4128624cbdd16be30f64966c67c08"
		},
		{
			"ImportPath": "github.com/gin-gonic/gin/render",
			"Comment": "v1.0rc1-110-g4cc2de6",
			"Rev": "4cc2de6207f4128624cbdd16be30f64966c67c08"
		},
		{
			"ImportPath": "github.com/lib/pq",
			"Comment": "go1.0-cutoff-96-gee1442b",
			"Rev": "ee1442bda7bd1b6a84e913bdb421cb1874ec629d"
		},
		{
			"ImportPath": "github.com/lib/pq/oid",
			"Comment": "go1.0-cutoff-96-gee1442b",
			"Rev": "ee1442bda7bd1b6a84e913bdb421cb1874ec629d"
		},
		{
			"ImportPath": "github.com/manucorporat/sse",
			"Rev": "c142f0f1baea5cef7f98a8a6c222f6134368c1f5"
		},
		{
			"ImportPath": "github.com/mattn/go-colorable",
			"Rev": "40e4aedc8fabf8c23e040057540867186712faa5"
		},
		{
			"ImportPath": "github.com/mattn/go-isatty",
			"Rev": "7fcbc72f853b92b5720db4a6b8482be612daef24"
		},
		{
			"ImportPath": "github.com/pmezard/go-difflib/difflib",
			"Rev": "792786c7400a136282c1664665ae0a8db921c6c2"
		},
		{
			"ImportPath": "github.com/russross/blackfriday",
			"Comment": "v1.4-31-g2004188",
			"Rev": "2004188462c3946efefbdcd91aa83e49b4175bfb"
		},
		{
			"ImportPath": "github.com/shurcooL/sanitized_anchor_name",
			"Rev": "10ef21a441db47d8b13ebcc5fd2310f636973c77"
		},
		{
			"ImportPath": "github.com/stretchr/testify/assert",
			"Comment": "v1.1.3-16-g6cb3b85",
			"Rev": "6cb3b85ef5a0efef77caef88363ec4d4b5c0976d"
		},
		{
			"ImportPath": "github.com/stretchr/testify/require",
			"Comment": "v1.1.3-16-g6cb3b85",
			"Rev": "6cb3b85ef5a0efef77caef88363ec4d4b5c0976d"
		},
		{
			"ImportPath": "github.com/stretchr/testify/suite",
			"Comment": "v1.1.3-16-g6cb3b85",
			"Rev": "6cb3b85ef5a0efef77caef88363ec4d4b5c0976d"
		},
		{
			"ImportPath": "golang.org/x/net/context",
			"Rev": "d9558e5c97f85372afee28cf2b6059d7d3818919"
		},
		{
			"ImportPath": "gopkg.in/bluesuncorp/validator.v5",
			"Comment": "v5.9.1",
			"Rev": "d627af88ac021317a280d320986282a6dc97549a"
		}
	]
}
